Workbook

Sheet Sheet1
A4: Margarita Garcia | C4: 24565
A5: Jorge Garcia | C5: 23686
A8: Full drop | B8: 345326 | C8: 07/01/2021/06/30/2029
A10: Pension | B10: =B8*0.96*0.96*0.96/12/8 -> 3182.5244
A12: Sick days | B12: =750*37.5 -> 28125
A13: Social age 62 | B13: 1800
A15: Expenses | B15: 3700
A18: Husband is sick for 5 years and Maggie is taking care of him

Sheet Sheet2
E2: 1 | F2: 2 | G2: 3 | H2: 4 | I2: 5 | J2: 6 | K2: 7 | L2: 8 | M2: 9 | N2: 10 | O2: 11 | P2: 12 | Q2: 13 | R2: 14 | S2: 15 | T2: 16 | U2: 17 | V2: 18 | W2: 19 | X2: 20 | Y2: 21 | Z2: 22 | AA2: 23 | AB2: 24 | AC2: 25 | AD2: 26
C3: Assets | D3: Age Jorge | E3: =2029-1964 -> 65 | F3: =E3+1 -> 66 | G3: =F3+1 -> 67 | H3: =G3+1 -> 68 | I3: =H3+1 -> 69 | J3: =I3+1 -> 70 | K3: =J3+1 -> 71 | L3: =K3+1 -> 72 | M3: =L3+1 -> 73 | ... AD3: =AC3+1 -> 90
D4: Age Maggie | E4: =2029-1967 -> 62 | F4: =E4+1 -> 63 | G4: =F4+1 -> 64 | H4: =G4+1 -> 65 | I4: =H4+1 -> 66 | J4: =I4+1 -> 67 | K4: =J4+1 -> 68 | L4: =K4+1 -> 69 | M4: =L4+1 -> 70 | ... AD4: =AC4+1 -> 87
D5: Year | E5: 2029 | F5: =E5+1 -> 2030 | G5: =F5+1 -> 2031 | H5: =G5+1 -> 2032 | I5: =H5+1 -> 2033 | J5: =I5+1 -> 2034 | K5: =J5+1 -> 2035 | L5: =K5+1 -> 2036 | M5: =L5+1 -> 2037 | ... AD5: =AC5+1 -> 2054
D6: DROP | E6: =Sheet1!B8 -> 345326 | F6: =E6*1.05 -> 362592.3 | G6: =F6*1.05 -> 380721.91 | H6: =G6*1.05 -> 399758.01 | I6: =H6*1.05 -> 419745.91 | J6: =I6*1.05 -> 440733.21 | K6: =J6*1.05 -> 462769.87 | L6: =K6*1.05 -> 485908.36 | M6: =L6*1.05 -> 510203.78 | ... P6: =O6*1.05 -> 590624.65 | Q6: =P6 -> 590624.65 | R6: =Q6 -> 590624.65 | S6: =R6 -> 590624.65 | T6: =S6 -> 590624.65 | U6: =T6 -> 590624.65 | V6: =U6 -> 590624.65 | W6: =V6 -> 590624.65 | X6: =W6 -> 590624.65 | ... AD6: =AC6 -> 590624.65
E7: =SUM(E6:E6) -> 345326 | F7: =SUM(F6:F6) -> 362592.3 | G7: =SUM(G6:G6) -> 380721.91 | H7: =SUM(H6:H6) -> 399758.01 | I7: =SUM(I6:I6) -> 419745.91 | J7: =SUM(J6:J6) -> 440733.21 | K7: =SUM(K6:K6) -> 462769.87 | L7: =SUM(L6:L6) -> 485908.36 | ... AD7: =SUM(AD6:AD6) -> 590624.65
C9: Income | D9: FRS Pension | E9: 3183 | F9: =E9*1.02 -> 3246.66 | G9: =F9*1.02 -> 3311.5932 | H9: =G9*1.02 -> 3377.8251 | I9: =H9*1.02 -> 3445.3816 | J9: =I9*1.02 -> 3514.2892 | K9: =J9*1.02 -> 3584.575 | L9: =K9*1.02 -> 3656.2665 | M9: =L9*1.02 -> 3729.3918 | ... AD9: =AC9*1.02 -> 5222.0489
D10: Social Security Maggie | E10: =Sheet1!B13 -> 1800 | F10: =E10*1.02 -> 1836 | G10: =F10*1.02 -> 1872.72 | H10: =G10*1.02 -> 1910.1744 | I10: =H10*1.02 -> 1948.3779 | J10: =I10*1.02 -> 1987.3454 | K10: =J10*1.02 -> 2027.0924 | L10: =K10*1.02 -> 2067.6342 | M10: =L10*1.02 -> 2108.9869 | ... AD10: =AC10*1.02 -> 2953.0908
D11: Social Security Jorge | E11: 1200 | F11: =E11*1.02 -> 1224 | G11: =F11*1.02 -> 1248.48 | H11: =G11*1.02 -> 1273.4496 | I11: =H11*1.02 -> 1298.9186 | J11: =I11*1.02 -> 1324.897 | K11: =J11*1.02 -> 1351.3949 | L11: =K11*1.02 -> 1378.4228 | M11: =L11*1.02 -> 1405.9913 | ... AD11: =AC11*1.02 -> 1968.7272
D12: Income from assets | E12: 0 | F12: =E12*1.02 -> 0 | G12: 0 | H12: 0 | I12: 0 | J12: 0 | K12: 0 | L12: 0 | M12: 0 | N12: 0 | O12: 0 | P12: =P7*5%/12 -> 2460.936 | Q12: =Q7*5%/12 -> 2460.936 | R12: =R7*5%/12 -> 2460.936 | S12: =S7*5%/12 -> 2460.936 | T12: =T7*5%/12 -> 2460.936 | U12: =U7*5%/12 -> 2460.936 | V12: =V7*5%/12 -> 2460.936 | W12: =W7*5%/12 -> 2460.936 | ... AD12: =AD7*5%/12 -> 2460.936
D13: Total monthly income | E13: =SUM(E9:E12) -> 6183 | F13: =SUM(F9:F12) -> 6306.66 | G13: =SUM(G9:G12) -> 6432.7932 | H13: =SUM(H9:H12) -> 6561.4491 | I13: =SUM(I9:I12) -> 6692.678 | J13: =SUM(J9:J12) -> 6826.5316 | K13: =SUM(K9:K12) -> 6963.0622 | L13: =SUM(L9:L12) -> 7102.3235 | ... AD13: =SUM(AD9:AD12) -> 12604.803
D15: Gross Taxable income | E15: =(E9+E12)*12+(E10+E11)*12*0.85 -> 68796 | F15: =(F9+F12)*12+(F10+F11)*12*0.85 -> 70171.92 | G15: =(G9+G12)*12+(G10+G11)*12*0.85 -> 71575.358 | H15: =(H9+H12)*12+(H10+H11)*12*0.85 -> 73006.866 | I15: =(I9+I12)*12+(I10+I11)*12*0.85 -> 74467.003 | J15: =(J9+J12)*12+(J10+J11)*12*0.85 -> 75956.343 | K15: =(K9+K12)*12+(K10+K11)*12*0.85 -> 77475.47 | L15: =(L9+L12)*12+(L10+L11)*12*0.85 -> 79024.979 | ... AD15: =(AD9+AD12)*12+(AD10+AD11)*12*0.85 -> 142398.36
D16: Standard Deduction | E16: 32200 | F16: =E16 -> 32200 | G16: =F16 -> 32200 | H16: =G16 -> 32200 | I16: =H16 -> 32200 | J16: =I16 -> 32200 | K16: =J16 -> 32200 | L16: =K16 -> 32200 | M16: =L16 -> 32200 | ... AD16: =AC16 -> 32200
D17: Social Security deduction | E17: 6000 | F17: 6000 | G17: 6000 | H17: 12000 | I17: 12000 | J17: 12000 | K17: 12000 | L17: 12000 | M17: 12000 | N17: 12000 | O17: 12000 | P17: 12000 | Q17: 12000 | R17: 12000 | S17: 12000 | T17: 12000 | U17: 12000 | V17: 12000 | W17: 12000 | X17: 12000 | Y17: 12000 | Z17: 12000 | AA17: 12000 | AB17: 12000 | AC17: 12000 | AD17: 12000
D18: Taxable Income | E18: =E15-E16-E17 -> 30596 | F18: =F15-F16-F17 -> 31971.92 | G18: =G15-G16-G17 -> 33375.358 | H18: =H15-H16-H17 -> 28806.866 | I18: =I15-I16-I17 -> 30267.003 | J18: =J15-J16-J17 -> 31756.343 | K18: =K15-K16-K17 -> 33275.47 | L18: =L15-L16-L17 -> 34824.979 | ... AD18: =AD15-AD16-AD17 -> 98198.362
B19: Tax Brackets
B20: 0 | C20: 24800 | D20: 0.1 | E20: =(C20-B20)*D20 -> 2480 | F20: =E20 -> 2480 | G20: =F20 -> 2480 | H20: =G20 -> 2480 | I20: =H20 -> 2480 | J20: =I20 -> 2480 | K20: =J20 -> 2480 | L20: =K20 -> 2480 | M20: =L20 -> 2480 | ... AD20: =AC20 -> 2480 | AE20: =(C20-B20)*D20 -> 2480
B21: 24800 | C21: 100800 | D21: 0.12 | E21: =(E18-$B$21)*$D$21 -> 695.52 | F21: =(F18-$B$21)*$D$21 -> 860.6304 | G21: =(G18-$B$21)*$D$21 -> 1029.043 | H21: =(H18-$B$21)*$D$21 -> 480.82387 | I21: =(I18-$B$21)*$D$21 -> 656.04035 | J21: =(J18-$B$21)*$D$21 -> 834.76115 | K21: =(K18-$B$21)*$D$21 -> 1017.0564 | L21: =(L18-$B$21)*$D$21 -> 1202.9975 | ... AD21: =(AD18-$B$21)*$D$21 -> 8807.8035 | AE21: =(C21-B21)*D21 -> 9120
B22: 100800 | C22: 211400 | D22: 0.22 | AE22: =(C22-B22)*D22 -> 24332
B23: 211400 | C23: 403550 | D23: 0.24 | AE23: =(C23-B23)*D23 -> 46116
B24: 403550 | C24: 512450 | D24: 0.32 | AE24: =(C24-B24)*D24 -> 34848
B25: 512450 | C25: 768700 | D25: 0.35 | AE25: =(AD7-B25)*D25 -> 27361.127
B26: 768700 | D26: 0.37
D27: Annual taxes | E27: =SUM(E20:E26) -> 3175.52 | F27: =SUM(F20:F26) -> 3340.6304 | G27: =SUM(G20:G26) -> 3509.043 | H27: =SUM(H20:H26) -> 2960.8239 | I27: =SUM(I20:I26) -> 3136.0403 | J27: =SUM(J20:J26) -> 3314.7612 | K27: =SUM(K20:K26) -> 3497.0564 | L27: =SUM(L20:L26) -> 3682.9975 | ... AE27: =SUM(AE20:AE26) -> 144257.13
D28: Monthly taxes | E28: =E27/12 -> 264.62667 | F28: =F27/12 -> 278.38587 | G28: =G27/12 -> 292.42025 | H28: =H27/12 -> 246.73532 | I28: =I27/12 -> 261.3367 | J28: =J27/12 -> 276.2301 | K28: =K27/12 -> 291.42136 | L28: =L27/12 -> 306.91646 | ... AD28: =AD27/12 -> 940.65029
D29: Net Monthly income | E29: =E13-E28 -> 5918.3733 | F29: =F13-F28 -> 6028.2741 | G29: =G13-G28 -> 6140.3729 | H29: =H13-H28 -> 6314.7137 | I29: =I13-I28 -> 6431.3413 | J29: =J13-J28 -> 6550.3015 | K29: =K13-K28 -> 6671.6409 | L29: =L13-L28 -> 6795.407 | ... AD29: =AD13-AD28 -> 11664.153
D30: Net Annual income | E30: =E29*12 -> 71020.48 | F30: =F29*12 -> 72339.29 | G30: =G29*12 -> 73684.475 | H30: =H29*12 -> 75776.565 | I30: =I29*12 -> 77176.096 | J30: =J29*12 -> 78603.618 | K30: =K29*12 -> 80059.69 | L30: =L29*12 -> 81544.884 | ... AD30: =AD29*12 -> 139969.83 | AE30: =SUM(E30:AD30) -> 2758728
D32: Monthly Expenses | E32: 3700 | F32: =E32*1.02 -> 3774 | G32: =F32*1.02 -> 3849.48 | H32: =G32*1.02 -> 3926.4696 | I32: =H32*1.02 -> 4004.999 | J32: =I32*1.02 -> 4085.099 | K32: =J32*1.02 -> 4166.801 | L32: =Sheet1!B15 -> 3700 | M32: =L32*1.02 -> 3774 | N32: =M32*1.02 -> 3849.48 | O32: =N32*1.02 -> 3926.4696 | P32: =O32*1.02 -> 4004.999 | Q32: =P32*1.02 -> 4085.099 | R32: =Q32*1.02 -> 4166.801 | S32: =R32*1.02 -> 4250.137 | T32: =S32*1.02 -> 4335.1397 | ... AD32: =AC32*1.02 -> 5284.5111
D34: Surplus income | E34: =E29-E32 -> 2218.3733 | F34: =F29-F32 -> 2254.2741 | G34: =G29-G32 -> 2290.8929 | H34: =H29-H32 -> 2388.2441 | I34: =I29-I32 -> 2426.3424 | J34: =J29-J32 -> 2465.2025 | K34: =K29-K32 -> 2504.8399 | L34: =L29-L32 -> 3095.407 | ... AD34: =AD29-AD32 -> 6379.6415
AE36: =AD7-AE27 -> 446367.52
P37: =P7-(0.1*MIN(P7,24800)+0.12*MAX(0,MIN(P7,100800)-24800)+0.22*MAX(0,MIN(P7,211400)-100800)+0.24*MAX(0,MIN(P7,403550)-211400)+0.32*MAX(0,MIN(P7,512450)-403550)+0.35*MAX(0,MIN(P7,768700)-512450)+0.37*MAX(0,P7-768700)) -> 446367.52
D38: Roth Growth Rate | E38: 0.08 | I38: Scenario | J38: Taxes 62-72 | K38: Scenario | L38: Taxes 73-90 | M38: Total | N38: After tax assets age73 | O38: Inheritance age 90 | V38: Pre Roth | W38: Assets Age 73
I39: No Roth conversion | J39: =SUM(E27:O27) -> 38819.074 | K39: No Roth conversion | L39: =SUM(P27:AD27) -> 143667.98 | M39: =L39+J39 -> 182487.05 | N39: =P37 -> 446367.52 | O39: =AE36 -> 446367.52 | V39: Taxable | W39: =W7 -> 590624.65
I40: With Roth conversion | J40: =SUM(Roth!E28:O28) -> 90926.434 | K40: With Roth conversion | L40: =SUM(Roth!P28:AD28) -> 90511.779 | M40: =L40+J40 -> 181438.21 | N40: =Roth!P8 -> 712851.3 | O40: =Roth!AD8 -> 2093782.3 | V40: Tax Equivalent | W40: =W39*0.76 -> 448874.73
M41: =M39-M40 -> 1048.8415 | N41: =N40-N39 -> 266483.78 | O41: =O40-O39 -> 1647414.8

Sheet Roth
E2: 1 | F2: 2 | G2: 3 | H2: 4 | I2: 5 | J2: 6 | K2: 7 | L2: 8 | M2: 9 | N2: 10 | O2: 11 | P2: 12 | Q2: 13 | R2: 14 | S2: 15 | T2: 16 | U2: 17 | V2: 18 | W2: 19 | X2: 20 | Y2: 21 | Z2: 22 | AA2: 23 | AB2: 24 | AC2: 25 | AD2: 26
C3: Assets | D3: Age Jorge | E3: =2029-1964 -> 65 | F3: =E3+1 -> 66 | G3: =F3+1 -> 67 | H3: =G3+1 -> 68 | I3: =H3+1 -> 69 | J3: =I3+1 -> 70 | K3: =J3+1 -> 71 | L3: =K3+1 -> 72 | M3: =L3+1 -> 73 | ... AD3: =AC3+1 -> 90
D4: Age Maggie | E4: =2029-1967 -> 62 | F4: =E4+1 -> 63 | G4: =F4+1 -> 64 | H4: =G4+1 -> 65 | I4: =H4+1 -> 66 | J4: =I4+1 -> 67 | K4: =J4+1 -> 68 | L4: =K4+1 -> 69 | M4: =L4+1 -> 70 | ... AD4: =AC4+1 -> 87
D5: Year | E5: 2029 | F5: =E5+1 -> 2030 | G5: =F5+1 -> 2031 | H5: =G5+1 -> 2032 | I5: =H5+1 -> 2033 | J5: =I5+1 -> 2034 | K5: =J5+1 -> 2035 | L5: =K5+1 -> 2036 | M5: =L5+1 -> 2037 | ... AD5: =AC5+1 -> 2054
D6: DROP | E6: =Sheet1!B8-E8 -> 305326 | F6: =E6*1.05-F8 -> 280592.3 | G6: =F6*1.05-G8 -> 254621.91 | H6: =G6*1.05-H8 -> 227353.01 | I6: =H6*1.05-I8 -> 198720.66 | J6: =I6*1.05-J8 -> 168656.69 | K6: =J6*1.05-K8 -> 137089.53 | L6: =K6*1.05-L8 -> 103944.01 | M6: =L6*1.05-M8 -> 69141.206 | ... O6: =N6*1.05-O8 -> 0.1793935 | P6: =O6*1.05 -> 0.18836317 | Q6: =P6 -> 0.18836317 | R6: =Q6 -> 0.18836317 | S6: =R6 -> 0.18836317 | T6: =S6 -> 0.18836317 | U6: =T6 -> 0.18836317 | V6: =U6 -> 0.18836317 | W6: =V6 -> 0.18836317 | X6: =W6 -> 0.18836317 | ... AD6: =AC6 -> 0.18836317
E7: =SUM(E6:E6) -> 305326 | F7: =SUM(F6:F6) -> 280592.3 | G7: =SUM(G6:G6) -> 254621.91 | H7: =SUM(H6:H6) -> 227353.01 | I7: =SUM(I6:I6) -> 198720.66 | J7: =SUM(J6:J6) -> 168656.69 | K7: =SUM(K6:K6) -> 137089.53 | L7: =SUM(L6:L6) -> 103944.01 | ... AD7: =SUM(AD6:AD6) -> 0.18836317
D8: Roth | E8: 40000 | F8: =$E$8 -> 40000 | G8: =$E$8 -> 40000 | H8: =$E$8 -> 40000 | I8: =$E$8 -> 40000 | J8: =$E$8 -> 40000 | K8: =$E$8 -> 40000 | L8: =$E$8 -> 40000 | M8: =$E$8 -> 40000 | N8: =$E$8 -> 40000 | O8: 34228 | P8: =E8*(1+$E$39)^11+F8*(1+$E$39)^10+G8*(1+$E$39)^9+H8*(1+$E$39)^8+I8*(1+$E$39)^7+J8*(1+$E$39)^6+K8*(1+$E$39)^5+L8*(1+$E$39)^4+M8*(1+$E$39)^3+N8*(1+$E$39)^2+O8*(1+$E$39)^1 -> 712851.3 | Q8: =P8*(1+$E$39) -> 769879.4 | R8: =Q8*(1+$E$39) -> 831469.75 | S8: =R8*(1+$E$39) -> 897987.33 | T8: =S8*(1+$E$39) -> 969826.32 | U8: =T8*(1+$E$39) -> 1047412.4 | V8: =U8*(1+$E$39) -> 1131205.4 | W8: =V8*(1+$E$39) -> 1221701.9 | X8: =W8*(1+$E$39) -> 1319438 | ... AD8: =AC8*(1+$E$39) -> 2093782.3
C10: Income | D10: FRS Pension | E10: =Sheet2!E9 -> 3183 | F10: =E10*1.02 -> 3246.66 | G10: =F10*1.02 -> 3311.5932 | H10: =G10*1.02 -> 3377.8251 | I10: =H10*1.02 -> 3445.3816 | J10: =I10*1.02 -> 3514.2892 | K10: =J10*1.02 -> 3584.575 | L10: =K10*1.02 -> 3656.2665 | M10: =L10*1.02 -> 3729.3918 | ... AD10: =AC10*1.02 -> 5222.0489
D11: Social Security Maggie | E11: =1800 -> 1800 | F11: =E11*1.02 -> 1836 | G11: =F11*1.02 -> 1872.72 | H11: =G11*1.02 -> 1910.1744 | I11: =H11*1.02 -> 1948.3779 | J11: =I11*1.02 -> 1987.3454 | K11: =J11*1.02 -> 2027.0924 | L11: =K11*1.02 -> 2067.6342 | M11: =L11*1.02 -> 2108.9869 | ... AD11: =AC11*1.02 -> 2953.0908
D12: Social Security Jorge | E12: 1200 | F12: =E12*1.02 -> 1224 | G12: =F12*1.02 -> 1248.48 | H12: =G12*1.02 -> 1273.4496 | I12: =H12*1.02 -> 1298.9186 | J12: =I12*1.02 -> 1324.897 | K12: =J12*1.02 -> 1351.3949 | L12: =K12*1.02 -> 1378.4228 | M12: =L12*1.02 -> 1405.9913 | ... AD12: =AC12*1.02 -> 1968.7272
D13: Income from assets | E13: 0 | F13: 0 | G13: 0 | H13: 0 | I13: 0 | J13: 0 | K13: 0 | L13: =K13 -> 0 | M13: =L13 -> 0 | N13: =M13 -> 0 | O13: =N13 -> 0 | P13: =P7*5%/12 -> 0.00078484655 | Q13: =P13 -> 0.00078484655 | R13: =Q13 -> 0.00078484655 | S13: =R13 -> 0.00078484655 | T13: =S13 -> 0.00078484655 | U13: =T13 -> 0.00078484655 | V13: =U13 -> 0.00078484655 | W13: =V13 -> 0.00078484655 | X13: =W13 -> 0.00078484655 | ... AD13: =AC13 -> 0.00078484655
D14: Total monthly income | E14: =SUM(E10:E13) -> 6183 | F14: =SUM(F10:F13) -> 6306.66 | G14: =SUM(G10:G13) -> 6432.7932 | H14: =SUM(H10:H13) -> 6561.4491 | I14: =SUM(I10:I13) -> 6692.678 | J14: =SUM(J10:J13) -> 6826.5316 | K14: =SUM(K10:K13) -> 6963.0622 | L14: =SUM(L10:L13) -> 7102.3235 | ... AD14: =SUM(AD10:AD13) -> 10143.868
D16: Gross Taxable income | E16: =(E10+E13)*12+(E11+E12)*12*0.85+E8 -> 108796 | F16: =(F10+F13)*12+(F11+F12)*12*0.85+F8 -> 110171.92 | G16: =(G10+G13)*12+(G11+G12)*12*0.85+G8 -> 111575.36 | H16: =(H10+H13)*12+(H11+H12)*12*0.85+H8 -> 113006.87 | I16: =(I10+I13)*12+(I11+I12)*12*0.85+I8 -> 114467 | J16: =(J10+J13)*12+(J11+J12)*12*0.85+J8 -> 115956.34 | K16: =(K10+K13)*12+(K11+K12)*12*0.85+K8 -> 117475.47 | L16: =(L10+L13)*12+(L11+L12)*12*0.85+L8 -> 119024.98 | ... O16: =(O10+O13)*12+(O11+O12)*12*0.85+O8 -> 118089.94 | P16: =(P10+P13)*12+(P11+P12)*12*0.85 -> 85539.188 | Q16: =(Q10+Q13)*12+(Q11+Q12)*12*0.85 -> 87249.972 | R16: =(R10+R13)*12+(R11+R12)*12*0.85 -> 88994.971 | S16: =(S10+S13)*12+(S11+S12)*12*0.85 -> 90774.87 | T16: =(T10+T13)*12+(T11+T12)*12*0.85 -> 92590.368 | U16: =(U10+U13)*12+(U11+U12)*12*0.85 -> 94442.175 | V16: =(V10+V13)*12+(V11+V12)*12*0.85 -> 96331.018 | W16: =(W10+W13)*12+(W11+W12)*12*0.85 -> 98257.638 | ... AD16: =(AD10+AD13)*12+(AD11+AD12)*12*0.85 -> 112867.14
D17: Standard Deduction | E17: 32200 | F17: =E17 -> 32200 | G17: =F17 -> 32200 | H17: =G17 -> 32200 | I17: =H17 -> 32200 | J17: =I17 -> 32200 | K17: =J17 -> 32200 | L17: =K17 -> 32200 | M17: =L17 -> 32200 | ... AD17: =AC17 -> 32200
D18: Social Security deduction | E18: 6000 | F18: =E18 -> 6000 | G18: =F18 -> 6000 | H18: 12000 | I18: =H18 -> 12000 | J18: =I18 -> 12000 | K18: =J18 -> 12000 | L18: =K18 -> 12000 | M18: =L18 -> 12000 | N18: =M18 -> 12000 | O18: =N18 -> 12000 | P18: =O18 -> 12000 | ... AD18: =AC18 -> 12000
D19: Taxable Income | E19: =E16-E17-E18 -> 70596 | F19: =F16-F17-F18 -> 71971.92 | G19: =G16-G17-G18 -> 73375.358 | H19: =H16-H17-H18 -> 68806.866 | I19: =I16-I17-I18 -> 70267.003 | J19: =J16-J17-J18 -> 71756.343 | K19: =K16-K17-K18 -> 73275.47 | L19: =L16-L17-L18 -> 74824.979 | ... AD19: =AD16-AD17-AD18 -> 68667.139
B20: Tax Brackets
B21: 0 | C21: 24800 | D21: 0.1 | E21: =(C21-B21)*D21 -> 2480 | F21: =E21 -> 2480 | G21: =F21 -> 2480 | H21: =G21 -> 2480 | I21: =H21 -> 2480 | J21: =I21 -> 2480 | K21: =J21 -> 2480 | L21: =K21 -> 2480 | M21: =L21 -> 2480 | ... AD21: =AC21 -> 2480 | AE21: =(C21-B21)*D21 -> 2480
B22: 24800 | C22: 100800 | D22: 0.12 | E22: =(E19-$B$22)*$D$22 -> 5495.52 | F22: =(F19-$B$22)*$D$22 -> 5660.6304 | G22: =(G19-$B$22)*$D$22 -> 5829.043 | H22: =(H19-$B$22)*$D$22 -> 5280.8239 | I22: =(I19-$B$22)*$D$22 -> 5456.0403 | J22: =(J19-$B$22)*$D$22 -> 5634.7612 | K22: =(K19-$B$22)*$D$22 -> 5817.0564 | L22: =(L19-$B$22)*$D$22 -> 6002.9975 | ... AD22: =(AD19-$B$22)*$D$22 -> 5264.0567 | AE22: =(C22-B22)*D22 -> 9120
B23: 100800 | C23: 211400 | D23: 0.22 | AE23: =(C23-B23)*D23 -> 24332
B24: 211400 | C24: 403550 | D24: 0.24 | AE24: =(C24-B24)*D24 -> 46116
B25: 403550 | C25: 512450 | D25: 0.32 | AE25: =(C25-B25)*D25 -> 34848
B26: 512450 | C26: 768700 | D26: 0.35 | AE26: =(AD7-B26)*D26 -> -179357.43
B27: 768700 | D27: 0.37
D28: Annual taxes | E28: =SUM(E21:E27) -> 7975.52 | F28: =SUM(F21:F27) -> 8140.6304 | G28: =SUM(G21:G27) -> 8309.043 | H28: =SUM(H21:H27) -> 7760.8239 | I28: =SUM(I21:I27) -> 7936.0403 | J28: =SUM(J21:J27) -> 8114.7612 | K28: =SUM(K21:K27) -> 8297.0564 | L28: =SUM(L21:L27) -> 8482.9975 | ... AE28: =SUM(AE21:AE27) -> -62461.434
D29: Monthly taxes | E29: =E28/12 -> 664.62667 | F29: =F28/12 -> 678.38587 | G29: =G28/12 -> 692.42025 | H29: =H28/12 -> 646.73532 | I29: =I28/12 -> 661.3367 | J29: =J28/12 -> 676.2301 | K29: =K28/12 -> 691.42136 | L29: =L28/12 -> 706.91646 | ... AD29: =AD28/12 -> 645.33806
D30: Net Monthly income | E30: =E14-E29 -> 5518.3733 | F30: =F14-F29 -> 5628.2741 | G30: =G14-G29 -> 5740.3729 | H30: =H14-H29 -> 5914.7137 | I30: =I14-I29 -> 6031.3413 | J30: =J14-J29 -> 6150.3015 | K30: =K14-K29 -> 6271.6409 | L30: =L14-L29 -> 6395.407 | ... AD30: =AD14-AD29 -> 9498.5296
D31: Net Annual income | E31: =E30*12 -> 66220.48 | F31: =F30*12 -> 67539.29 | G31: =G30*12 -> 68884.475 | H31: =H30*12 -> 70976.565 | I31: =I30*12 -> 72376.096 | J31: =J30*12 -> 73803.618 | K31: =K30*12 -> 75259.69 | L31: =L30*12 -> 76744.884 | ... AD31: =AD30*12 -> 113982.36 | AE31: =SUM(E31:AD31) -> 2316808.4
D33: Monthly Expenses | E33: =Sheet1!B15 -> 3700 | F33: =E33*1.02 -> 3774 | G33: =F33*1.02 -> 3849.48 | H33: =G33*1.02 -> 3926.4696 | I33: =H33*1.02 -> 4004.999 | J33: =I33*1.02 -> 4085.099 | K33: =J33*1.02 -> 4166.801 | L33: =K33*1.02 -> 4250.137 | M33: =L33*1.02 -> 4335.1397 | ... AD33: =AC33*1.02 -> 6070.2422
D35: Surplus income | E35: =E30-E33 -> 1818.3733 | F35: =F30-F33 -> 1854.2741 | G35: =G30-G33 -> 1890.8929 | H35: =H30-H33 -> 1988.2441 | I35: =I30-I33 -> 2026.3424 | J35: =J30-J33 -> 2065.2025 | K35: =K30-K33 -> 2104.8399 | L35: =L30-L33 -> 2145.2701 | ... AD35: =AD30-AD33 -> 3428.2874
AE37: =AD7-AE28 -> 62461.622
D39: Roth Growth Rate | E39: 0.08 | O39: Pre Roth | P39: Assets Age 73
O40: Tax Free | P40: =P8 -> 712851.3
